{
    "process_parameters": {
        "parameters_names": [
            "algorithm_name",
            "GD_gloablMaxThreads",
            "GD_maxThreads",
            "gloablMaxThreads",
            "maxThreads",
            "maxRetries",
            "sleepTime",
            "test_param_scheduling_threshold",
            "GD_algorithmName",
            "GD_consideraFestivos",
            "GD_convenioBD"
        ],

        "parameters_defaults": {
            "algorithm_name": "salsa_algorithm",
            "GD_gloablMaxThreads": 4,
            "GD_maxThreads": 2,
            "gloablMaxThreads": 4,
            "maxThreads": 2,
            "maxRetries": 3,
            "sleepTime": 1000,
            "test_param_scheduling_threshold": 0.75,
            "GD_algorithmName": "alcampo_algorithm",
            "GD_consideraFestivos": 1,
            "GD_convenioBD": "ALCAMPO"
        }
    }, 
    
    "external_call_data": {
        "current_process_id": 2637,
        "api_proc_id": 999,
        "wfm_proc_id": 2637,
        "wfm_user": "WFM",
        "start_date": "2025-01-01",
        "end_date": "2025-12-31",
        "wfm_proc_colab": null
    }
}